[
   {
      "path": {
         "module": "",
         "scope": [],
         "name": "null"
      },
      "children": [
         {
            "path": {
               "module": "",
               "scope": [],
               "name": "Object"
            },
            "children": [
               {
                  "path": {
                     "module": "",
                     "scope": [],
                     "name": "Function"
                  },
                  "children": []
               },
               {
                  "path": {
                     "module": "",
                     "scope": [],
                     "name": "Array"
                  },
                  "children": []
               },
               {
                  "path": {
                     "module": "",
                     "scope": [],
                     "name": "Number"
                  },
                  "children": []
               },
               {
                  "path": {
                     "module": "",
                     "scope": [],
                     "name": "Boolean"
                  },
                  "children": []
               },
               {
                  "path": {
                     "module": "",
                     "scope": [],
                     "name": "String"
                  },
                  "children": []
               },
               {
                  "path": {
                     "module": "",
                     "scope": [],
                     "name": "Symbol"
                  },
                  "children": []
               },
               {
                  "path": {
                     "module": "",
                     "scope": [],
                     "name": "Date"
                  },
                  "children": []
               },
               {
                  "path": {
                     "module": "",
                     "scope": [],
                     "name": "Promise"
                  },
                  "children": []
               },
               {
                  "path": {
                     "module": "",
                     "scope": [],
                     "name": "RegExp"
                  },
                  "children": []
               },
               {
                  "path": {
                     "module": "",
                     "scope": [],
                     "name": "Error"
                  },
                  "children": [
                     {
                        "path": {
                           "module": "",
                           "scope": [],
                           "name": "EvalError"
                        },
                        "children": []
                     },
                     {
                        "path": {
                           "module": "",
                           "scope": [],
                           "name": "RangeError"
                        },
                        "children": []
                     },
                     {
                        "path": {
                           "module": "",
                           "scope": [],
                           "name": "ReferenceError"
                        },
                        "children": []
                     },
                     {
                        "path": {
                           "module": "",
                           "scope": [],
                           "name": "SyntaxError"
                        },
                        "children": []
                     },
                     {
                        "path": {
                           "module": "",
                           "scope": [],
                           "name": "TypeError"
                        },
                        "children": []
                     },
                     {
                        "path": {
                           "module": "",
                           "scope": [],
                           "name": "URIError"
                        },
                        "children": []
                     },
                     {
                        "path": {
                           "module": "",
                           "scope": [
                              "WebAssembly"
                           ],
                           "name": "CompileError"
                        },
                        "children": []
                     },
                     {
                        "path": {
                           "module": "",
                           "scope": [
                              "WebAssembly"
                           ],
                           "name": "LinkError"
                        },
                        "children": []
                     },
                     {
                        "path": {
                           "module": "",
                           "scope": [
                              "WebAssembly"
                           ],
                           "name": "RuntimeError"
                        },
                        "children": []
                     }
                  ]
               },
               {
                  "path": {
                     "module": "",
                     "scope": [
                        "Error"
                     ],
                     "name": "prepareStackTrace"
                  },
                  "children": []
               },
               {
                  "path": {
                     "module": "",
                     "scope": [
                        "console",
                        "_stdout",
                        "_events"
                     ],
                     "name": "onReadableStreamEnd"
                  },
                  "children": []
               },
               {
                  "path": {
                     "module": "",
                     "scope": [
                        "console",
                        "_stdout"
                     ],
                     "name": "destroy"
                  },
                  "children": []
               },
               {
                  "path": {
                     "module": "",
                     "scope": [
                        "console",
                        "_stdout"
                     ],
                     "name": "dummyDestroy"
                  },
                  "children": []
               },
               {
                  "path": {
                     "module": "",
                     "scope": [
                        "console"
                     ],
                     "name": "Console"
                  },
                  "children": []
               },
               {
                  "path": {
                     "module": "",
                     "scope": [
                        "Intl"
                     ],
                     "name": "DateTimeFormat"
                  },
                  "children": []
               },
               {
                  "path": {
                     "module": "",
                     "scope": [
                        "Intl"
                     ],
                     "name": "NumberFormat"
                  },
                  "children": []
               },
               {
                  "path": {
                     "module": "",
                     "scope": [
                        "Intl"
                     ],
                     "name": "Collator"
                  },
                  "children": []
               },
               {
                  "path": {
                     "module": "",
                     "scope": [
                        "Intl"
                     ],
                     "name": "PluralRules"
                  },
                  "children": []
               },
               {
                  "path": {
                     "module": "",
                     "scope": [
                        "Intl"
                     ],
                     "name": "RelativeTimeFormat"
                  },
                  "children": []
               },
               {
                  "path": {
                     "module": "",
                     "scope": [
                        "Intl"
                     ],
                     "name": "ListFormat"
                  },
                  "children": []
               },
               {
                  "path": {
                     "module": "",
                     "scope": [
                        "Intl"
                     ],
                     "name": "Locale"
                  },
                  "children": []
               },
               {
                  "path": {
                     "module": "",
                     "scope": [],
                     "name": "ArrayBuffer"
                  },
                  "children": []
               },
               {
                  "path": {
                     "module": "",
                     "scope": [],
                     "name": "TypedArray"
                  },
                  "children": [
                     {
                        "path": {
                           "module": "",
                           "scope": [],
                           "name": "Uint8Array"
                        },
                        "children": []
                     },
                     {
                        "path": {
                           "module": "",
                           "scope": [],
                           "name": "Int8Array"
                        },
                        "children": []
                     },
                     {
                        "path": {
                           "module": "",
                           "scope": [],
                           "name": "Uint16Array"
                        },
                        "children": []
                     },
                     {
                        "path": {
                           "module": "",
                           "scope": [],
                           "name": "Int16Array"
                        },
                        "children": []
                     },
                     {
                        "path": {
                           "module": "",
                           "scope": [],
                           "name": "Uint32Array"
                        },
                        "children": []
                     },
                     {
                        "path": {
                           "module": "",
                           "scope": [],
                           "name": "Int32Array"
                        },
                        "children": []
                     },
                     {
                        "path": {
                           "module": "",
                           "scope": [],
                           "name": "Float32Array"
                        },
                        "children": []
                     },
                     {
                        "path": {
                           "module": "",
                           "scope": [],
                           "name": "Float64Array"
                        },
                        "children": []
                     },
                     {
                        "path": {
                           "module": "",
                           "scope": [],
                           "name": "Uint8ClampedArray"
                        },
                        "children": []
                     },
                     {
                        "path": {
                           "module": "",
                           "scope": [],
                           "name": "BigUint64Array"
                        },
                        "children": []
                     },
                     {
                        "path": {
                           "module": "",
                           "scope": [],
                           "name": "BigInt64Array"
                        },
                        "children": []
                     }
                  ]
               },
               {
                  "path": {
                     "module": "",
                     "scope": [],
                     "name": "DataView"
                  },
                  "children": []
               },
               {
                  "path": {
                     "module": "",
                     "scope": [],
                     "name": "Map"
                  },
                  "children": []
               },
               {
                  "path": {
                     "module": "",
                     "scope": [],
                     "name": "BigInt"
                  },
                  "children": []
               },
               {
                  "path": {
                     "module": "",
                     "scope": [],
                     "name": "Set"
                  },
                  "children": []
               },
               {
                  "path": {
                     "module": "",
                     "scope": [],
                     "name": "WeakMap"
                  },
                  "children": []
               },
               {
                  "path": {
                     "module": "",
                     "scope": [],
                     "name": "WeakSet"
                  },
                  "children": []
               },
               {
                  "path": {
                     "module": "",
                     "scope": [],
                     "name": "SharedArrayBuffer"
                  },
                  "children": []
               },
               {
                  "path": {
                     "module": "",
                     "scope": [
                        "WebAssembly"
                     ],
                     "name": "compile"
                  },
                  "children": []
               },
               {
                  "path": {
                     "module": "",
                     "scope": [
                        "WebAssembly"
                     ],
                     "name": "validate"
                  },
                  "children": []
               },
               {
                  "path": {
                     "module": "",
                     "scope": [
                        "WebAssembly"
                     ],
                     "name": "instantiate"
                  },
                  "children": []
               },
               {
                  "path": {
                     "module": "",
                     "scope": [
                        "WebAssembly"
                     ],
                     "name": "Module"
                  },
                  "children": []
               },
               {
                  "path": {
                     "module": "",
                     "scope": [
                        "WebAssembly",
                        "Module"
                     ],
                     "name": "imports"
                  },
                  "children": []
               },
               {
                  "path": {
                     "module": "",
                     "scope": [
                        "WebAssembly",
                        "Module"
                     ],
                     "name": "exports"
                  },
                  "children": []
               },
               {
                  "path": {
                     "module": "",
                     "scope": [
                        "WebAssembly",
                        "Module"
                     ],
                     "name": "customSections"
                  },
                  "children": []
               },
               {
                  "path": {
                     "module": "",
                     "scope": [
                        "WebAssembly"
                     ],
                     "name": "Instance"
                  },
                  "children": []
               },
               {
                  "path": {
                     "module": "",
                     "scope": [
                        "WebAssembly"
                     ],
                     "name": "Table"
                  },
                  "children": []
               },
               {
                  "path": {
                     "module": "",
                     "scope": [
                        "WebAssembly"
                     ],
                     "name": "Memory"
                  },
                  "children": []
               },
               {
                  "path": {
                     "module": "",
                     "scope": [
                        "WebAssembly"
                     ],
                     "name": "Global"
                  },
                  "children": []
               },
               {
                  "path": {
                     "module": "",
                     "scope": [
                        "process"
                     ],
                     "name": "_rawDebug"
                  },
                  "children": []
               },
               {
                  "path": {
                     "module": "",
                     "scope": [
                        "process"
                     ],
                     "name": "binding"
                  },
                  "children": []
               },
               {
                  "path": {
                     "module": "",
                     "scope": [
                        "process"
                     ],
                     "name": "_linkedBinding"
                  },
                  "children": []
               },
               {
                  "path": {
                     "module": "",
                     "scope": [
                        "process",
                        "_events"
                     ],
                     "name": "onWarning"
                  },
                  "children": []
               },
               {
                  "path": {
                     "module": "",
                     "scope": [
                        "process",
                        "_events",
                        "newListener"
                     ],
                     "name": "startListeningIfSignal"
                  },
                  "children": []
               },
               {
                  "path": {
                     "module": "",
                     "scope": [
                        "process",
                        "_events",
                        "removeListener"
                     ],
                     "name": "stopListeningIfSignal"
                  },
                  "children": []
               },
               {
                  "path": {
                     "module": "",
                     "scope": [
                        "process"
                     ],
                     "name": "umask"
                  },
                  "children": []
               },
               {
                  "path": {
                     "module": "",
                     "scope": [
                        "process"
                     ],
                     "name": "chdir"
                  },
                  "children": []
               },
               {
                  "path": {
                     "module": "",
                     "scope": [
                        "process"
                     ],
                     "name": "cwd"
                  },
                  "children": []
               },
               {
                  "path": {
                     "module": "",
                     "scope": [
                        "process"
                     ],
                     "name": "hrtime"
                  },
                  "children": []
               },
               {
                  "path": {
                     "module": "",
                     "scope": [
                        "process",
                        "hrtime"
                     ],
                     "name": "hrtimeBigInt"
                  },
                  "children": []
               },
               {
                  "path": {
                     "module": "",
                     "scope": [
                        "process"
                     ],
                     "name": "cpuUsage"
                  },
                  "children": []
               },
               {
                  "path": {
                     "module": "",
                     "scope": [
                        "process"
                     ],
                     "name": "resourceUsage"
                  },
                  "children": []
               },
               {
                  "path": {
                     "module": "",
                     "scope": [
                        "process"
                     ],
                     "name": "memoryUsage"
                  },
                  "children": []
               },
               {
                  "path": {
                     "module": "",
                     "scope": [
                        "process"
                     ],
                     "name": "kill"
                  },
                  "children": []
               },
               {
                  "path": {
                     "module": "",
                     "scope": [
                        "process"
                     ],
                     "name": "exit"
                  },
                  "children": []
               },
               {
                  "path": {
                     "module": "",
                     "scope": [
                        "process"
                     ],
                     "name": "initgroups"
                  },
                  "children": []
               },
               {
                  "path": {
                     "module": "",
                     "scope": [
                        "process"
                     ],
                     "name": "setgroups"
                  },
                  "children": []
               },
               {
                  "path": {
                     "module": "",
                     "scope": [
                        "process"
                     ],
                     "name": ""
                  },
                  "children": []
               },
               {
                  "path": {
                     "module": "",
                     "scope": [
                        "process"
                     ],
                     "name": ""
                  },
                  "children": []
               },
               {
                  "path": {
                     "module": "",
                     "scope": [
                        "process"
                     ],
                     "name": ""
                  },
                  "children": []
               },
               {
                  "path": {
                     "module": "",
                     "scope": [
                        "process"
                     ],
                     "name": ""
                  },
                  "children": []
               },
               {
                  "path": {
                     "module": "",
                     "scope": [
                        "process"
                     ],
                     "name": ""
                  },
                  "children": []
               },
               {
                  "path": {
                     "module": "",
                     "scope": [
                        "process"
                     ],
                     "name": "deprecated"
                  },
                  "children": []
               },
               {
                  "path": {
                     "module": "",
                     "scope": [
                        "process"
                     ],
                     "name": ""
                  },
                  "children": []
               },
               {
                  "path": {
                     "module": "",
                     "scope": [
                        "process"
                     ],
                     "name": "hasUncaughtExceptionCaptureCallback"
                  },
                  "children": []
               },
               {
                  "path": {
                     "module": "",
                     "scope": [
                        "process"
                     ],
                     "name": "emitWarning"
                  },
                  "children": []
               },
               {
                  "path": {
                     "module": "",
                     "scope": [
                        "process"
                     ],
                     "name": "nextTick"
                  },
                  "children": []
               },
               {
                  "path": {
                     "module": "",
                     "scope": [
                        "process"
                     ],
                     "name": "runNextTicks"
                  },
                  "children": []
               },
               {
                  "path": {
                     "module": "",
                     "scope": [
                        "process",
                        "mainModule",
                        "children",
                        "0",
                        "exports"
                     ],
                     "name": "pruneTree"
                  },
                  "children": []
               },
               {
                  "path": {
                     "module": "",
                     "scope": [
                        "process",
                        "mainModule",
                        "children",
                        "0",
                        "exports"
                     ],
                     "name": "sortTree"
                  },
                  "children": []
               },
               {
                  "path": {
                     "module": "",
                     "scope": [
                        "process",
                        "mainModule",
                        "children",
                        "0",
                        "exports"
                     ],
                     "name": "parseModule"
                  },
                  "children": []
               },
               {
                  "path": {
                     "module": "",
                     "scope": [
                        "process",
                        "mainModule",
                        "children",
                        "0",
                        "children",
                        "0",
                        "exports"
                     ],
                     "name": "clamp"
                  },
                  "children": []
               },
               {
                  "path": {
                     "module": "",
                     "scope": [
                        "process",
                        "mainModule",
                        "children",
                        "0",
                        "children",
                        "0",
                        "exports"
                     ],
                     "name": "className"
                  },
                  "children": []
               },
               {
                  "path": {
                     "module": "",
                     "scope": [
                        "process",
                        "mainModule",
                        "children",
                        "0",
                        "children",
                        "0",
                        "exports"
                     ],
                     "name": "escapeRegExp"
                  },
                  "children": []
               },
               {
                  "path": {
                     "module": "",
                     "scope": [
                        "process",
                        "mainModule",
                        "children",
                        "0",
                        "children",
                        "0",
                        "exports"
                     ],
                     "name": "isConstructor"
                  },
                  "children": []
               },
               {
                  "path": {
                     "module": "",
                     "scope": [
                        "process",
                        "mainModule",
                        "children",
                        "0",
                        "children",
                        "0",
                        "exports"
                     ],
                     "name": "not"
                  },
                  "children": []
               },
               {
                  "path": {
                     "module": "",
                     "scope": [
                        "process",
                        "mainModule",
                        "children",
                        "0",
                        "children",
                        "0",
                        "exports"
                     ],
                     "name": "writeJSON"
                  },
                  "children": []
               },
               {
                  "path": {
                     "module": "",
                     "scope": [
                        "process",
                        "mainModule",
                        "children",
                        "0",
                        "children",
                        "0"
                     ],
                     "name": ""
                  },
                  "children": []
               },
               {
                  "path": {
                     "module": "",
                     "scope": [
                        "process",
                        "mainModule",
                        "children",
                        "0"
                     ],
                     "name": ""
                  },
                  "children": []
               },
               {
                  "path": {
                     "module": "",
                     "scope": [
                        "process",
                        "mainModule"
                     ],
                     "name": ""
                  },
                  "children": []
               },
               {
                  "path": {
                     "module": "",
                     "scope": [
                        "process"
                     ],
                     "name": ""
                  },
                  "children": []
               },
               {
                  "path": {
                     "module": "",
                     "scope": [
                        "Buffer"
                     ],
                     "name": "from"
                  },
                  "children": []
               },
               {
                  "path": {
                     "module": "",
                     "scope": [
                        "Buffer"
                     ],
                     "name": "alloc"
                  },
                  "children": []
               },
               {
                  "path": {
                     "module": "",
                     "scope": [
                        "Buffer"
                     ],
                     "name": "allocUnsafe"
                  },
                  "children": []
               },
               {
                  "path": {
                     "module": "",
                     "scope": [
                        "Buffer"
                     ],
                     "name": "allocUnsafeSlow"
                  },
                  "children": []
               },
               {
                  "path": {
                     "module": "",
                     "scope": [
                        "Buffer"
                     ],
                     "name": "isBuffer"
                  },
                  "children": []
               },
               {
                  "path": {
                     "module": "",
                     "scope": [
                        "Buffer"
                     ],
                     "name": "compare"
                  },
                  "children": []
               },
               {
                  "path": {
                     "module": "",
                     "scope": [
                        "Buffer"
                     ],
                     "name": "isEncoding"
                  },
                  "children": []
               },
               {
                  "path": {
                     "module": "",
                     "scope": [
                        "Buffer"
                     ],
                     "name": "concat"
                  },
                  "children": []
               },
               {
                  "path": {
                     "module": "",
                     "scope": [
                        "Buffer"
                     ],
                     "name": "byteLength"
                  },
                  "children": []
               },
               {
                  "path": {
                     "module": "",
                     "scope": [],
                     "name": "URL"
                  },
                  "children": []
               },
               {
                  "path": {
                     "module": "",
                     "scope": [],
                     "name": "URLSearchParams"
                  },
                  "children": []
               },
               {
                  "path": {
                     "module": "",
                     "scope": [],
                     "name": "TextEncoder"
                  },
                  "children": []
               },
               {
                  "path": {
                     "module": "",
                     "scope": [],
                     "name": "TextDecoder"
                  },
                  "children": []
               }
            ]
         }
      ]
   },
   {
      "path": {
         "module": "",
         "scope": [
            "console",
            "_stdout",
            "_writableState"
         ],
         "name": "bound onwrite"
      },
      "children": []
   },
   {
      "path": {
         "module": "",
         "scope": [
            "console",
            "_stdout",
            "_writableState",
            "corkedRequestsFree"
         ],
         "name": "bound onCorkedFinish"
      },
      "children": []
   },
   {
      "path": {
         "module": "",
         "scope": [
            "console",
            "_stderr",
            "_writableState"
         ],
         "name": "bound onwrite"
      },
      "children": []
   },
   {
      "path": {
         "module": "",
         "scope": [
            "console",
            "_stderr",
            "_writableState",
            "corkedRequestsFree"
         ],
         "name": "bound onCorkedFinish"
      },
      "children": []
   },
   {
      "path": {
         "module": "",
         "scope": [],
         "name": "Proxy"
      },
      "children": []
   },
   {
      "path": {
         "module": "",
         "scope": [
            "process",
            "stdin",
            "_writableState"
         ],
         "name": "bound onwrite"
      },
      "children": []
   },
   {
      "path": {
         "module": "",
         "scope": [
            "process",
            "stdin",
            "_writableState",
            "corkedRequestsFree"
         ],
         "name": "bound onCorkedFinish"
      },
      "children": []
   }
]